wolpert/__init__.py
wolpert/pipeline.py
wolpert/sklearn_pipeline.py
wolpert/wrappers/__init__.py
wolpert/wrappers/base.py
wolpert/wrappers/cross_val.py
wolpert/wrappers/holdout.py
wolpert/wrappers/time_series.py
wolpert-0.1.1.dist-info/LICENSE
wolpert-0.1.1.dist-info/METADATA
wolpert-0.1.1.dist-info/WHEEL
wolpert-0.1.1.dist-info/top_level.txt
wolpert-0.1.1.dist-info/RECORD
